{
  "gitSyncId": "6788b4e942ee4f76ed394a35_b6dd6651-3ec2-4229-ac22-b57ee937f551",
  "id": "Page1__$JSModule11$_JSModule1.myFun21",
  "isPublic": true,
  "moduleInstanceId": "Page1_JSModule11",
  "pluginId": "js-plugin",
  "pluginType": "JS",
  "rootModuleInstanceId": "Page1_JSModule11",
  "unpublishedAction": {
    "collectionId": "Page1__$JSModule11$_JSModule1",
    "confirmBeforeExecute": false,
    "contextType": "PAGE",
    "datasource": {
      "isAutoGenerated": false,
      "name": "UNUSED_DATASOURCE",
      "pluginId": "js-plugin"
    },
    "executeOnLoad": false,
    "fullyQualifiedName": "_$JSModule11$_JSModule1.myFun21",
    "name": "myFun21",
    "pageId": "Page1",
    "userSetOnLoad": false
  }
}